odoo/addons/developer_menu/README.rst
odoo/addons/developer_menu/__init__.py
odoo/addons/developer_menu/__manifest__.py
odoo/addons/developer_menu/i18n/developer_menu.pot
odoo/addons/developer_menu/i18n/it.po
odoo/addons/developer_menu/i18n/vi_VN.po
odoo/addons/developer_menu/readme/CONTRIBUTORS.md
odoo/addons/developer_menu/readme/DESCRIPTION.md
odoo/addons/developer_menu/readme/USAGE.md
odoo/addons/developer_menu/static/description/icon.png
odoo/addons/developer_menu/static/description/index.html
odoo/addons/developer_menu/static/description/menu.png
odoo/addons/developer_menu/views/menu_view.xml
odoo_addon_developer_menu-18.0.1.0.0.5.dist-info/METADATA
odoo_addon_developer_menu-18.0.1.0.0.5.dist-info/WHEEL
odoo_addon_developer_menu-18.0.1.0.0.5.dist-info/top_level.txt
odoo_addon_developer_menu-18.0.1.0.0.5.dist-info/RECORD
